{
  "updatedAt": "2026-04-02T09:13:00+01:00",
  "games": [
    {
      "name": "Assetto Corsa Evo",
      "latestVersion": "0.5.4",
      "updates": [
        {
          "id": "acevo-2026-03-16-update-054",
          "game": "Assetto Corsa Evo",
          "version": "0.5.4",
          "date": "2026-03-16",
          "headline": "Patch 0.5.4 fixes multiplayer cars failing to load at race start",
          "sourceName": "505 Games Support",
          "sourceUrl": "https://support.505games.com/support/solutions/articles/150000223050-assetto-corsa-evo-0-5-4-patch-notes",
          "status": "Official",
          "summary": "505 Games lists version 0.5.4 as the latest official ACEVO patch, focused on fixing cars not loading in time in multiplayer sessions at race start."
        },
        {
          "id": "acevo-2026-02-12-update-05",
          "game": "Assetto Corsa Evo",
          "version": "0.5",
          "date": "2026-02-12",
          "headline": "Update 0.5 adds Watkins Glen, Paul Ricard, new cars, and free camera mode",
          "sourceName": "Steam",
          "sourceUrl": "https://store.steampowered.com/app/3058630/Assetto_Corsa_EVO/",
          "status": "Official",
          "summary": "The main 0.5 release added seven cars, Watkins Glen and Paul Ricard, free camera mode, DLSS 4.5, blue flags, and broader track-limit and dynamic-track work that the 0.5 hotfixes build on."
        }
      ]
    },
    {
      "name": "Assetto Corsa Rally",
      "latestVersion": "0.3.1",
      "updates": [
        {
          "id": "acrally-2026-03-04-hotfix-031",
          "game": "Assetto Corsa Rally",
          "version": "0.3.1",
          "date": "2026-03-04",
          "headline": "Hotfix 0.3.1 fixes shifter gear-change problems on most models",
          "sourceName": "Steam Community",
          "sourceUrl": "https://steamcommunity.com/app/3917090/allnews/",
          "status": "Official",
          "summary": "Supernova Games Studios published Hotfix 0.3.1 as the latest official Assetto Corsa Rally build, addressing gear-change issues on most shifters and correcting the Spanish description for the new cars."
        },
        {
          "id": "acrally-2026-02-26-update-03",
          "game": "Assetto Corsa Rally",
          "version": "0.3",
          "date": "2026-02-26",
          "headline": "Update 0.3 brings Monte Carlo stages, dynamic snow, and two more rally cars",
          "sourceName": "Steam",
          "sourceUrl": "https://store.steampowered.com/app/3917090/Assetto_Corsa_Rally/",
          "status": "Official",
          "summary": "The Steam store and Steam Community both show 0.3 as the latest Early Access step, adding laser-scanned Monte Carlo stages at Col de Turini and Sisteron, dynamic snow and ice conditions, two new cars, and 40 new event entries."
        }
      ]
    },
    {
      "name": "Wreckfest 2",
      "latestVersion": "Content Update #6 Patch #4",
      "updates": [
        {
          "id": "wreckfest2-2026-03-27-content-update-06-patch-4",
          "game": "Wreckfest 2",
          "version": "Content Update #6 Patch #4",
          "date": "2026-03-27",
          "headline": "Patch #4 for Content Update #6 tightens paint-system rules and moderation tools",
          "sourceName": "Steam Community",
          "sourceUrl": "https://steamcommunity.com/app/1203190",
          "status": "Official",
          "summary": "The latest official Wreckfest 2 post on Steam Community is Content Update #6 Patch #4, which adds paint-system guidelines and improves moderation and player-reporting efficiency."
        },
        {
          "id": "wreckfest2-2026-03-05-content-update-06",
          "game": "Wreckfest 2",
          "version": "Content Update #6",
          "date": "2026-03-05",
          "headline": "Content Update #6 adds Hurricane, Nami, School Bus, Dalsbanen, Waypoint Race, and upgrades",
          "sourceName": "Steam Community",
          "sourceUrl": "https://store.steampowered.com/app/1203190/Wreckfest_2/",
          "status": "Official",
          "summary": "The main Content Update #6 rollout added three vehicles, the Dalsbanen track, the new Waypoint Race mode, eight challenges, the first car-upgrade system, dirt accumulation on all surfaces, and a wide batch of stability, UI, and audio improvements."
        }
      ]
    },
    {
      "name": "Crimson Desert",
      "latestVersion": "1.01.03",
      "updates": [
        {
          "id": "crimsondesert-2026-03-31-hotfix-10103",
          "game": "Crimson Desert",
          "version": "1.01.03",
          "date": "2026-03-31",
          "headline": "Hotfix 1.01.03 fixes bosses sometimes stopping during combat",
          "sourceName": "Pearl Abyss",
          "sourceUrl": "https://crimsondesert.pearlabyss.com/en-us/News/Notice/Detail?_boardNo=79",
          "status": "Official",
          "summary": "Pearl Abyss lists 1.01.03 as the newest official hotfix, deployed first on Steam PC, Steam Mac, PlayStation, Xbox, and Epic Games Store, with a fix for bosses freezing during combat."
        },
        {
          "id": "crimsondesert-2026-03-28-patch-10100",
          "game": "Crimson Desert",
          "version": "1.01.00",
          "date": "2026-03-28",
          "headline": "Patch 1.01.00 adds five summonable mounts and lowers fast-travel load times",
          "sourceName": "Pearl Abyss",
          "sourceUrl": "https://crimsondesert.pearlabyss.com/en-us/News/Notice/Detail?_boardNo=76",
          "status": "Official",
          "summary": "Pearl Abyss used 1.01.00 for the larger post-launch content drop, adding five summonable mounts, faster fast-travel and revival loading, and further control changes across supported platforms."
        }
      ]
    }
  ],
  "needsVerification": []
}
